odoo/addons/cooperator_api/README.rst
odoo/addons/cooperator_api/__init__.py
odoo/addons/cooperator_api/__manifest__.py
odoo/addons/cooperator_api/controllers/__init__.py
odoo/addons/cooperator_api/controllers/controllers.py
odoo/addons/cooperator_api/demo/demo.xml
odoo/addons/cooperator_api/i18n/cooperator_api.pot
odoo/addons/cooperator_api/migrations/12.0.2.0.0/pre-migration.py
odoo/addons/cooperator_api/models/__init__.py
odoo/addons/cooperator_api/models/auth_api_key.py
odoo/addons/cooperator_api/models/external_id_mixin.py
odoo/addons/cooperator_api/models/subscription_request.py
odoo/addons/cooperator_api/readme/CONTRIBUTORS.rst
odoo/addons/cooperator_api/readme/DESCRIPTION.rst
odoo/addons/cooperator_api/readme/ROADMAP.rst
odoo/addons/cooperator_api/readme/USAGE.rst
odoo/addons/cooperator_api/security/ir_rule.xml
odoo/addons/cooperator_api/services/__init__.py
odoo/addons/cooperator_api/services/abstract_cooperator_service.py
odoo/addons/cooperator_api/services/account_invoice_service.py
odoo/addons/cooperator_api/services/account_payment_service.py
odoo/addons/cooperator_api/services/ping_service.py
odoo/addons/cooperator_api/services/schemas.py
odoo/addons/cooperator_api/services/subscription_request_service.py
odoo/addons/cooperator_api/static/description/index.html
odoo/addons/cooperator_api/tests/__init__.py
odoo/addons/cooperator_api/tests/common.py
odoo/addons/cooperator_api/tests/test_account_invoice.py
odoo/addons/cooperator_api/tests/test_account_payment.py
odoo/addons/cooperator_api/tests/test_external_id_mixin.py
odoo/addons/cooperator_api/tests/test_ping.py
odoo/addons/cooperator_api/tests/test_registry.py
odoo/addons/cooperator_api/tests/test_subscription_requests.py
odoo/addons/cooperator_api/views/external_id_mixin_views.xml
odoo12_addon_cooperator_api-12.0.2.0.0.99.dev7.dist-info/METADATA
odoo12_addon_cooperator_api-12.0.2.0.0.99.dev7.dist-info/WHEEL
odoo12_addon_cooperator_api-12.0.2.0.0.99.dev7.dist-info/top_level.txt
odoo12_addon_cooperator_api-12.0.2.0.0.99.dev7.dist-info/RECORD
