Metadata-Version: 2.1
Name: odoo12-addon-cooperator-api
Version: 12.0.2.0.0.99.dev7
Summary: Open Cooperators to the world: RESTful API.
Home-page: https://coopiteasy.be
Author: Coop IT Easy SC
License: AGPL-3
Platform: UNKNOWN
Classifier: Programming Language :: Python
Classifier: Framework :: Odoo
Classifier: License :: OSI Approved :: GNU Affero General Public License v3
Requires-Python: >=3.5
Requires-Dist: odoo12-addon-auth-api-key
Requires-Dist: odoo12-addon-base-rest
Requires-Dist: odoo12-addon-cooperator
Requires-Dist: odoo12-addon-cooperator-api-logs
Requires-Dist: odoo (<12.1dev,>=12.0a)
